Metadata-Version: 2.3
Name: data-solutions-test-library
Version: 0.0.8
Summary: SDK functions for users to query Data Solutions databases.
Project-URL: Homepage, https://github.com/TransposeData/chainalysis-data-solutions-python-sdk
Author-email: "Rah Tarar (musa-tarar)" <musa.nishat@chainalysis.com>, "Kurt Bugbee (krtbgb)" <kurt.bugbee@chainalysis.com>
License-File: LICENCE
Classifier: License :: OSI Approved :: MIT License
Classifier: Operating System :: OS Independent
Classifier: Programming Language :: Python :: 3
Requires-Python: >=3.8
Requires-Dist: autoflake==2.3.1
Requires-Dist: pandas==2.2.2
Requires-Dist: requests==2.32.3
Requires-Dist: sqlalchemy==2.0.35
Requires-Dist: tenacity==9.0.0
Requires-Dist: tqdm==4.66.5
